[
    {
        "name":"Semen",
        "text":"СЕМЕН"
    },
    {
        "name":"OldWoman",
        "text":"БАБА НЮРА"
    },
    {
        "name":"Plumber",
        "text":"СЛЕСАРЬ СТЕПАНЫЧ"
    },
    {
        "name":"Hunk1",
        "text":"МИСТЕР ВСЕЛЕННАЯ"
    },
    {
        "name":"Hunk2",
        "text":"ПОДСНЕЖНИК"
    },
    {
        "name":"Hunk3",
        "text":"НОГИ-БАЗУКИ"
    },
    {
        "name":"CardsMan",
        "text":"КАРТЕЖНИК"
    },
    {
        "name":"FatMan",
        "text":"ТОЛСТЯК"
    },
    {
        "name":"Milf",
        "text":"ИРИНА"
    },
    {
        "name":"EmergencyButton",
        "text":"ТРЕВОЖНАЯ КНОПКА"
    },
    {
        "name":"Shaman",
        "text":"ШАМАН"
    },
    {
        "name":"MeMom",
        "text":"МАМА МАРИЯ"
    },
    {
        "name":"Shahtar",
        "text":"ВАСИЛЬИЧ"
    },
    {
        "name":"Major",
        "text":"МЭР"
    },
    {
        "name":"BfMajor",
        "text":"МЭР"
    },
    {
        "name":"CabCrew",
        "text":"ПРОВОДНИЦА"
    },
    {
        "name":"BfCabCrew",
        "text":"ПРОВОДНИЦА"
    },
    {
        "name":"MajorGirl",
        "text":"КАРИНА"
    },
    {
        "name":"Hunter",
        "text":"ВЕНИАМИН МИХАИЛОВИЧ"
    },
    {
        "name":"Grandmaster",
        "text":"ЛАВРЕНТИЙ ПАЛЫЧ"
    },
    {
        "name":"CardsMenBed",
        "text":"КОЙКА КАРТЕЖНИКА"
    },
    {
        "name":"OldWomansBed",
        "text":"КОЙКА БАБЫ НЮРЫ"
    },
    {
        "name":"MilfBed",
        "text":"КОЙКА ИРИНЫ"
    },
    {
        "name":"MinersBed",
        "text":"КОЙКА ШАХЕТРОВ"
    },
    {
        "name":"npc",
        "text":"ПАССАЖИР"
    }
]